Tool.py
ryouDemo/__init__.py
ryouDemo/demoTool.py
ryouDemo-0.0.1.dist-info/LICENSE.txt
ryouDemo-0.0.1.dist-info/METADATA
ryouDemo-0.0.1.dist-info/WHEEL
ryouDemo-0.0.1.dist-info/top_level.txt
ryouDemo-0.0.1.dist-info/RECORD
