Metadata-Version: 2.1
Name: ryouDemo
Version: 0.0.1
Summary: A demo package for Ryou
Home-page: https://space.bilibili.com/354814866?spm_id_from=333.1007.0.0
Author: Jeff Kafka
Author-email: qaqnoname@163.com
License: MIT
License-File: LICENSE.txt
